MANIFEST.in
Makefile
README
setup.py
markdown_checklists/__init__.py
markdown_checklists/checklists.js
markdown_checklists/extension.py
markdown_checklists.egg-info/PKG-INFO
markdown_checklists.egg-info/SOURCES.txt
markdown_checklists.egg-info/dependency_links.txt
markdown_checklists.egg-info/not-zip-safe
markdown_checklists.egg-info/requires.txt
markdown_checklists.egg-info/top_level.txt
test/__init__.py
test/test_main.py
test/__pycache__/__init__.cpython-34.pyc
test/__pycache__/test_main.cpython-34-PYTEST.pyc