Metadata-Version: 1.0
Name: markdown-checklists
Version: 0.5.2
Summary: Fork of Markdown-checklist: Python Markdown extension for task lists with checkboxes
Home-page: https://github.com/tobiashochguertel/markdown-checklists
Author: Tobias Hochguertel, FND
Author-email: tobias.hochguertel@googlemail.com
License: MIT
Platform: Posix; MacOS X; Windows
